LAB6/Data_Mem/Data_Mem.v
`timescale 1ns / 1ps

module Data_Mem #(
    parameter ADDR_WIDTH = 8,   // Default: 8-bit address (256 locations)
    parameter DATA_WIDTH = 64,  // Default: 64-bit data per entry
    parameter MEM_DEPTH = 256,  // Default: 256 memory entries
    parameter INIT_FILE = "Data_MM.hex" // Default memory initialization file
)(
    input wire clk,                            // Synchronous clock
    input wire Write_Enable,                   // Write Enable signal
    input wire [ADDR_WIDTH-1:0] Address,       // Single Address input (for both Read & Write)
    input wire [DATA_WIDTH-1:0] WData,         // Write Data input
    output reg [DATA_WIDTH-1:0] Dout           // Read Data output
);

    // Parameterized memory array
    reg [DATA_WIDTH-1:0] Memory [MEM_DEPTH-1:0];

    // Read Operation (Synchronous Read at posedge clk)
    always @(posedge clk)
    begin
        Dout <= Memory[Address]; // Read data from memory
    end

    // Write Operation (Triggered at negedge clk, controlled by Write_Enable)
    always @(negedge clk) 
    begin
        if (Write_Enable) 
        begin
            Memory[Address] <= WData; // Store data in memory at the same Address
        end
    end

    // Memory Preloading from File (if a file is specified)
    initial 
    begin
        if (INIT_FILE != "") // If INIT_FILE is provided, load memory contents
        begin
            $display("Loading memory from %s", INIT_FILE);
            $readmemh(INIT_FILE, Memory);
        end
    end

endmodule



// `timescale 1ns / 1ps

// module Data_Mem #(
//     parameter ADDR_WIDTH = 8,   // Default: 8-bit address (256 locations)
//     parameter DATA_WIDTH = 64,  // Default: 64-bit data per entry
//     parameter MEM_DEPTH = 256,  // Default: 256 memory entries
//     parameter INIT_FILE = "Data_MM.hex" // Default memory initialization file
// )(
//     input wire clk,                             // Synchronous clock
//     input wire Write_Enable,                    // Write Enable signal
//     input wire [ADDR_WIDTH-1:0] Read_Addr,      // Read Address
//     //input wire [ADDR_WIDTH-1:0] Write_Addr,     // Write Address
//     input wire [DATA_WIDTH-1:0] Write_Data,     // Input data to write
//     output reg [DATA_WIDTH-1:0] Read_Data       // Output data read from memory
// );
//     // Parameterized memory array
//     reg [DATA_WIDTH-1:0] Memory [MEM_DEPTH-1:0];

//     // Read Operation
//     always @(posedge clk)
//     begin
//         Read_Data <= Memory[Read_Addr]; // Load data from memory
//     end

//     // Write Operation (Triggered at negedge clk, controlled by Write_Enable)
//     always @(negedge clk) 
//     begin
//         if (Write_Enable) 
//         begin
//             Memory[Write_Addr] <= Write_Data; // Store data in memory
//         end
//     end

//     // Memory Preloading from File (if a file is specified)
//     initial 
//     begin
//         if (INIT_FILE != "") // If INIT_File is EMPTY
//         begin
//             $display("Loading memory from %s", INIT_FILE);
//             $readmemh(INIT_FILE, Memory);
//         end
//     end
// endmodule

LAB6/Data_Mem/tb_Data_Mem.v
`timescale 1ns / 1ps
`include "Data_Mem.v"

module tb_Data_Mem();

    // Testbench parameters (Ensure they match Data_Mem module)
    parameter ADDR_WIDTH = 8;   // Address width (8-bit = 256 locations)
    parameter DATA_WIDTH = 64;  // Data width (64-bit per entry)
    parameter MEM_DEPTH = 256;  // Memory depth (256 entries)

    // Signals for DUT (Device Under Test)
    reg clk;
    reg Write_Enable;
    reg [ADDR_WIDTH-1:0] Address;  // Single Address input
    reg [DATA_WIDTH-1:0] WData;    // Input Data for Writing
    wire [DATA_WIDTH-1:0] Dout;    // Output Data for Reading

    // Instantiate the Data_Mem Module
    Data_Mem #(
        .ADDR_WIDTH(ADDR_WIDTH),
        .DATA_WIDTH(DATA_WIDTH),
        .MEM_DEPTH(MEM_DEPTH),
        .INIT_FILE("Data_MM.hex") // Ensure a valid initialization file
    ) dut (
        .clk(clk),
        .Write_Enable(Write_Enable),
        .Address(Address),
        .WData(WData),
        .Dout(Dout)
    );

    // Clock Generation: 10ns period (5ns high, 5ns low)
    always #5 clk = ~clk; 

    // Task for Writing Data to Memory
    task Writing_data_Task(input [ADDR_WIDTH-1:0] addr, input [DATA_WIDTH-1:0] data);
    begin
        @(negedge clk); // Wait for negedge to align with write operation
        Write_Enable = 1;
        Address = addr;
        WData = data;
        @(negedge clk); // Hold write for one cycle
        Write_Enable = 0;
        $display("Time %0t: Wrote %0d to Memory[%0d]", $time, data, addr);
    end
    endtask

    // Task for Reading Data from Memory
    task Reading_data_task(input [ADDR_WIDTH-1:0] addr);
    begin
        @(posedge clk); // Wait for posedge to align with read operation
        Address = addr;
        @(posedge clk); // Hold for one cycle to ensure data stability
        $display("Time %0t: Read Memory[%0d] = %0d", $time, addr, Dout);
    end
    endtask

    // Test Sequence Using Tasks
    initial begin
        // Creating DUMP-FILE
        $dumpfile("waveform.vcd"); // Create VCD file
        $dumpvars(0, tb_Data_Mem); // Dump all variables

        // Initialize Signals
        clk = 0;
        Write_Enable = 0;
        Address = 0;
        WData = 0;

        //  Writing Test Data
        Writing_data_Task(8'd1, 64'd42);   // Write 42 to Memory[1]
        Writing_data_Task(8'd3, 64'd100);  // Write 100 to Memory[3]
        Writing_data_Task(8'd5, 64'd255);  // Write 255 to Memory[5]

        // Reading Back the Data
        Reading_data_task(8'd1);  // Read Memory[1]
        Reading_data_task(8'd3);  // Read Memory[3]
        Reading_data_task(8'd5);  // Read Memory[5]

        // Assertion Check
        @(posedge clk);
        if (Dout !== 64'd42) $display("ERROR: Memory[1] expected 42, got %0d", Dout);
        @(posedge clk);
        if (Dout !== 64'd100) $display("ERROR: Memory[3] expected 100, got %0d", Dout);
        @(posedge clk);
        if (Dout !== 64'd255) $display("ERROR: Memory[5] expected 255, got %0d", Dout);
        else $display("All memory tests passed!");

        // 🌟 End Simulation
        #20 $finish;
    end

endmodule


// `timescale 1ns / 1ps
// `include "Data_Mem.v"

// module tb_Data_Mem();

//     // Testbench parameters (Ensure they match Data_Mem module)
//     parameter ADDR_WIDTH = 8;   // Address width (8-bit = 256 locations)
//     parameter DATA_WIDTH = 64;  // Data width (64-bit per entry)
//     parameter MEM_DEPTH = 256;  // Memory depth (256 entries)

//     // Signals for DUT (Device Under Test)
//     reg clk;
//     reg Write_Enable;
//     reg [ADDR_WIDTH-1:0] Read_Addr;
//     reg [ADDR_WIDTH-1:0] Write_Addr;
//     reg [DATA_WIDTH-1:0] Write_Data;
//     wire [DATA_WIDTH-1:0] Read_Data; // Output wire

//     // Instantiate the Data_Mem Module
//     Data_Mem #(
//         .ADDR_WIDTH(ADDR_WIDTH),
//         .DATA_WIDTH(DATA_WIDTH),
//         .MEM_DEPTH(MEM_DEPTH),
//         .INIT_FILE("Data_MM.hex") // Ensure a valid initialization file
//     ) dut (
//         .clk(clk),
//         .Write_Enable(Write_Enable),
//         .Read_Addr(Read_Addr),
//         .Write_Addr(Write_Addr),
//         .Write_Data(Write_Data),
//         .Read_Data(Read_Data)
//     );

//     // Clock Generation: 10ns period (5ns high, 5ns low)
//     always #5 clk = ~clk; 

//     // 🚀 Task for Writing Data to Memory
//     task Writing_data_Task(input [ADDR_WIDTH-1:0] addr, input [DATA_WIDTH-1:0] data);
//     begin
//         @(negedge clk); // Wait for negedge to align with write operation
//         Write_Enable = 1;
//         Write_Addr = addr;
//         Write_Data = data;
//         @(negedge clk); // Hold write for one cycle
//         Write_Enable = 0;
//         $display("Time %0t: Wrote %0d to Memory[%0d]", $time, data, addr);
//     end
//     endtask

//     // 🚀 Task for Reading Data from Memory
//     task Reading_data_task(input [ADDR_WIDTH-1:0] addr);
//     begin
//         @(posedge clk); // Wait for posedge to align with read operation
//         Read_Addr = addr;
//         @(posedge clk); // Hold for one cycle to ensure data stability
//         $display("Time %0t: Read Memory[%0d] = %0d", $time, addr, Read_Data);
//     end
//     endtask

//     // 🌟 Test Sequence Using Tasks
//     initial begin
//         // Creating DUMP-FILE
//         $dumpfile("waveform.vcd"); // Create VCD file
//         $dumpvars(0, tb_Data_Mem); // Dump all variables
//         // Initialize Signals
//         clk = 0;
//         Write_Enable = 0;
//         Read_Addr = 0;
//         Write_Addr = 0;
//         Write_Data = 0;

//         // 🚀 Writing Test Data
//         Writing_data_Task(8'd1, 64'd42);   // Write 42 to Memory[1]
//         Writing_data_Task(8'd3, 64'd100);  // Write 100 to Memory[3]
//         Writing_data_Task(8'd5, 64'd255);  // Write 255 to Memory[5]

//         // 🌟 Reading Back the Data
//         Reading_data_task(8'd1);  // Read Memory[1]
//         Reading_data_task(8'd3);  // Read Memory[3]
//         Reading_data_task(8'd5);  // Read Memory[5]

//         // ✅ Assertion Check
//         @(posedge clk);
//         if (Read_Data !== 64'd42) $display("❌ ERROR: Memory[1] expected 42, got %0d", Read_Data);
//         @(posedge clk);
//         if (Read_Data !== 64'd100) $display("❌ ERROR: Memory[3] expected 100, got %0d", Read_Data);
//         @(posedge clk);
//         if (Read_Data !== 64'd255) $display("❌ ERROR: Memory[5] expected 255, got %0d", Read_Data);
//         else $display("✅ All memory tests passed!");

//         // 🌟 End Simulation
//         #20 $finish;
//     end

// endmodule

LAB6/Data_Mem/waveform.vcd
$date
	Fri Feb 21 16:35:39 2025
$end
$version
	Icarus Verilog
$end
$timescale
	1ps
$end
$scope module tb_Data_Mem $end
$var wire 64 ! Dout [63:0] $end
$var parameter 32 " ADDR_WIDTH $end
$var parameter 32 # DATA_WIDTH $end
$var parameter 32 $ MEM_DEPTH $end
$var reg 8 % Address [7:0] $end
$var reg 64 & WData [63:0] $end
$var reg 1 ' Write_Enable $end
$var reg 1 ( clk $end
$scope module dut $end
$var wire 8 ) Address [7:0] $end
$var wire 64 * WData [63:0] $end
$var wire 1 ' Write_Enable $end
$var wire 1 ( clk $end
$var parameter 32 + ADDR_WIDTH $end
$var parameter 32 , DATA_WIDTH $end
$var parameter 88 - INIT_FILE $end
$var parameter 32 . MEM_DEPTH $end
$var reg 64 / Dout [63:0] $end
$upscope $end
$scope task Reading_data_task $end
$var reg 8 0 addr [7:0] $end
$upscope $end
$scope task Writing_data_Task $end
$var reg 8 1 addr [7:0] $end
$var reg 64 2 data [63:0] $end
$upscope $end
$upscope $end
$enddefinitions $end
$comment Show the parameter values. $end
$dumpall
b100000000 .
b100010001100001011101000110000101011111010011010100110100101110011010000110010101111000 -
b1000000 ,
b1000 +
b100000000 $
b1000000 #
b1000 "
$end
#0
$dumpvars
b101010 2
b1 1
bx 0
bx /
b0 *
b0 )
0(
0'
b0 &
b0 %
bx !
$end
#5000
1(
#10000
b101010 &
b101010 *
b1 %
b1 )
1'
0(
#15000
1(
#20000
b1100100 2
b11 1
0'
0(
#25000
1(
#30000
b1100100 &
b1100100 *
b11 %
b11 )
1'
0(
#35000
b1100100 !
b1100100 /
1(
#40000
b11111111 2
b101 1
0'
0(
#45000
1(
#50000
b11111111 &
b11111111 *
b101 %
b101 )
1'
0(
#55000
b11111111 !
b11111111 /
1(
#60000
b1 0
0'
0(
#65000
bx !
bx /
b1 %
b1 )
1(
#70000
0(
#75000
b11 0
1(
#80000
0(
#85000
b1100100 !
b1100100 /
b11 %
b11 )
1(
#90000
0(
#95000
b101 0
1(
#100000
0(
#105000
b11111111 !
b11111111 /
b101 %
b101 )
1(
